mini/__init__.py
mini/chunker.py
mini/embedding.py
mini/loader.py
mini/logger.py
mini/observability.py
mini/rag.py
mini/reranker.py
mini/store.py
mini/documents/eb_test.pdf
mini_rag-0.1.3.dist-info/METADATA
mini_rag-0.1.3.dist-info/WHEEL
mini_rag-0.1.3.dist-info/licenses/LICENSE
mini_rag-0.1.3.dist-info/RECORD
