Metadata-Version: 2.4
Name: mini-rag
Version: 0.1.3
Summary: A lightweight RAG (Retrieval-Augmented Generation) library with document loading, chunking, embedding, vector storage, and re-ranking
Project-URL: Homepage, https://github.com/vivek12345/mini-rag
Project-URL: Documentation, https://github.com/vivek12345/mini-rag#readme
Project-URL: Repository, https://github.com/vivek12345/mini-rag
Project-URL: Issues, https://github.com/vivek12345/mini-rag/issues
Author-email: Vivek N <vivek.of.nayyar@gmail.com>
Maintainer-email: Vivek N <vivek.of.nayyar@gmail.com>
License: MIT
License-File: LICENSE
Keywords: ai,embeddings,llm,nlp,rag,retrieval,semantic-search,vector-search
Classifier: Development Status :: 5 - Production/Stable
Classifier: Intended Audience :: Developers
Classifier: License :: OSI Approved :: MIT License
Classifier: Programming Language :: Python :: 3
Classifier: Programming Language :: Python :: 3.11
Classifier: Programming Language :: Python :: 3.12
Classifier: Topic :: Scientific/Engineering :: Artificial Intelligence
Classifier: Topic :: Software Development :: Libraries :: Python Modules
Requires-Python: >=3.11
Requires-Dist: chonkie[hub,openai,viz]>=1.4.1
Requires-Dist: cohere>=5.0.0
Requires-Dist: langfuse>=2.0.0
Requires-Dist: markitdown[all]>=0.1.3
Requires-Dist: openai>=1.0.0
Requires-Dist: pydantic>=2.12.4
Requires-Dist: pymilvus>=2.5.0
Requires-Dist: python-dotenv>=1.2.1
Requires-Dist: sentence-transformers>=2.2.0
